magic_logger.py
magic_logger-1.0.1.dist-info/METADATA
magic_logger-1.0.1.dist-info/WHEEL
magic_logger-1.0.1.dist-info/top_level.txt
magic_logger-1.0.1.dist-info/RECORD
