Metadata-Version: 2.1
Name: magic-logger
Version: 1.0.1
Summary: This very simple module does its best to help you use Python's logging correctly, by making sure you always invoke the right Logger for a module.
Home-page: https://github.com/RaduG/magic_logger
Author: Radu Ghitescu
Author-email: radu.ghitescu@gmail.com
License: MIT
Platform: UNKNOWN
Classifier: Development Status :: 5 - Production/Stable
Classifier: Intended Audience :: Developers
Requires-Python: >=3.6
